chromoplot/__init__.py
chromoplot/cli/__init__.py
chromoplot/cli/main.py
chromoplot/core/__init__.py
chromoplot/core/coordinates.py
chromoplot/core/figure.py
chromoplot/core/regions.py
chromoplot/io/__init__.py
chromoplot/io/bam.py
chromoplot/io/bed.py
chromoplot/io/fasta.py
chromoplot/io/gff.py
chromoplot/io/paf.py
chromoplot/io/synteny.py
chromoplot/layouts/__init__.py
chromoplot/layouts/base.py
chromoplot/layouts/comparative.py
chromoplot/layouts/genome.py
chromoplot/layouts/linear.py
chromoplot/themes/__init__.py
chromoplot/themes/colors.py
chromoplot/themes/theme.py
chromoplot/tracks/__init__.py
chromoplot/tracks/alignment.py
chromoplot/tracks/annotation.py
chromoplot/tracks/base.py
chromoplot/tracks/depth.py
chromoplot/tracks/feature.py
chromoplot/tracks/gene.py
chromoplot/tracks/haplotype.py
chromoplot/tracks/ideogram.py
chromoplot/tracks/scale.py
chromoplot/tracks/signal.py
chromoplot/tracks/synteny.py
chromoplot/tracks/variant.py
chromoplot-0.1.0.dist-info/METADATA
chromoplot-0.1.0.dist-info/WHEEL
chromoplot-0.1.0.dist-info/entry_points.txt
chromoplot-0.1.0.dist-info/licenses/LICENSE
chromoplot-0.1.0.dist-info/RECORD
