Metadata-Version: 2.4
Name: chromoplot
Version: 0.1.0
Summary: Flexible genome visualization toolkit for publication-ready figures
Project-URL: Homepage, https://github.com/aseetharam/chromoplot
Project-URL: Repository, https://github.com/aseetharam/chromoplot
Author-email: Arun Seetharam <your.email@purdue.edu>
License: MIT
License-File: LICENSE
Keywords: bioinformatics,genome browser,genomics,matplotlib,visualization
Classifier: Development Status :: 3 - Alpha
Classifier: Intended Audience :: Science/Research
Classifier: License :: OSI Approved :: MIT License
Classifier: Operating System :: OS Independent
Classifier: Programming Language :: Python :: 3
Classifier: Programming Language :: Python :: 3.10
Classifier: Programming Language :: Python :: 3.11
Classifier: Programming Language :: Python :: 3.12
Classifier: Topic :: Scientific/Engineering :: Bio-Informatics
Classifier: Topic :: Scientific/Engineering :: Visualization
Requires-Python: >=3.10
Requires-Dist: click>=8.0
Requires-Dist: matplotlib>=3.7
Requires-Dist: numpy>=1.24
Requires-Dist: pandas>=2.0
Requires-Dist: pyyaml>=6.0
Provides-Extra: dev
Requires-Dist: pytest-cov>=4.0; extra == 'dev'
Requires-Dist: pytest>=7.0; extra == 'dev'
Requires-Dist: ruff>=0.1; extra == 'dev'
Provides-Extra: full
Requires-Dist: pybigwig>=0.3; extra == 'full'
Requires-Dist: pysam>=0.21; extra == 'full'
